sample3/__init__.py
sample3/analysis.py
sample3/preprocessing.py
xpsfshg-0.0.4.dist-info/LICENSE
xpsfshg-0.0.4.dist-info/METADATA
xpsfshg-0.0.4.dist-info/WHEEL
xpsfshg-0.0.4.dist-info/top_level.txt
xpsfshg-0.0.4.dist-info/RECORD
